LICENSE
godoo_rpc/__init__.py
godoo_rpc/api.py
godoo_rpc/file_2_odoo.py
godoo_rpc/helpers/env.py
godoo_rpc/helpers/importer.py
godoo_rpc/helpers/pandas/dataset.py
godoo_rpc/helpers/pandas/read.py
godoo_rpc/helpers/rpc.py
godoo_rpc/importers/__init__.py
godoo_rpc/importers/import_csv.py
godoo_rpc/importers/import_data.py
godoo_rpc/importers/import_product_images.py
godoo_rpc/importers/import_settings.py
godoo_rpc/importers/import_translation.py
godoo_rpc/importers/import_xl.py
godoo_rpc/login.py
godoo_rpc/odoo2odoo_mapper.py
godoo_rpc/odoo_dataset.py
godoo_rpc-0.1.4.dist-info/LICENSE
godoo_rpc-0.1.4.dist-info/METADATA
godoo_rpc-0.1.4.dist-info/WHEEL
godoo_rpc-0.1.4.dist-info/RECORD
