Metadata-Version: 2.1
Name: godoo-rpc
Version: 0.1.4
Summary: Helper Functions around OdooRPC
Home-page: https://github.com/OpenJKSoftware/gOdoo-rpc
License: LGPL-3
Keywords: odoorpc,odoo
Author: Joshua Kreuder
Author-email: joshua_kreuder@outlook.com
Requires-Python: >=3.9
Classifier: License :: Other/Proprietary License
Classifier: Programming Language :: Python :: 3
Classifier: Programming Language :: Python :: 3.9
Classifier: Programming Language :: Python :: 3.10
Classifier: Programming Language :: Python :: 3.11
Classifier: Programming Language :: Python :: 3.12
Requires-Dist: OdooRPC (>=0.9.0)
Requires-Dist: openpyxl (>=3.0.10)
Requires-Dist: pandas (>=2.1.4)
Requires-Dist: pylint-gitlab (>=1.1.0)
Requires-Dist: python-dotenv (>=0.20.0)
Requires-Dist: requests (>=2.25.1)
Project-URL: Repository, https://github.com/OpenJKSoftware/gOdoo-rpc
